tkinterPdfViewer/__init__.py
tkinterPdfViewer/tkinterPdfViewer.py
tkinterPdfViewer-0.2.dist-info/LICENSE
tkinterPdfViewer-0.2.dist-info/METADATA
tkinterPdfViewer-0.2.dist-info/WHEEL
tkinterPdfViewer-0.2.dist-info/top_level.txt
tkinterPdfViewer-0.2.dist-info/RECORD
