Metadata-Version: 2.1
Name: tkinterPdfViewer
Version: 0.2
Summary: The tkinterPdfViewer is python library, which allows you to embed the PDF file in your tkinter GUI
Home-page: https://github.com/Fahad-codecraft
Author: Fahad Devnikar
Author-email: devnikarfahad@gmail.com
License: MIT
Keywords: PdfViewer,tkinter,pdf
Classifier: Development Status :: 3 - Alpha
Classifier: Intended Audience :: Developers
Classifier: Topic :: Software Development :: Build Tools
Classifier: License :: OSI Approved :: MIT License
Classifier: Programming Language :: Python :: 3
License-File: LICENSE
Requires-Dist: PyMuPDF
Requires-Dist: customtkinter
